Pymenulist/__init__.py
Pymenulist-1.1.2.dist-info/METADATA
Pymenulist-1.1.2.dist-info/WHEEL
Pymenulist-1.1.2.dist-info/top_level.txt
Pymenulist-1.1.2.dist-info/RECORD
