Metadata-Version: 2.1
Name: Pymenulist
Version: 1.1.2
Summary: Create console menu
Home-page: UNKNOWN
Author: Rushpy
Author-email: oivan4218@gmail.com
License: UNKNOWN
Platform: UNKNOWN
Classifier: Programming Language :: Python :: 3
Classifier: License :: OSI Approved :: MIT License
Classifier: Operating System :: OS Independent
Requires-Python: >=3.6
